sp_ask_school/__init__.py
sp_ask_school/schools.py
sp_ask_school-0.3.9.dist-info/METADATA
sp_ask_school-0.3.9.dist-info/WHEEL
sp_ask_school-0.3.9.dist-info/RECORD
