Metadata-Version: 2.1
Name: sp-ask-school
Version: 0.3.9
Summary: A package for managing school information and queues for Scholars Portal Ask
Home-page: https://github.com/scholarsportal/ask_schools
License: MIT
Keywords: school,queue,management,scholars portal,ask a librarian
Author: Guinsly Mondésir
Requires-Python: >=3.8,<4.0
Classifier: Development Status :: 4 - Beta
Classifier: Intended Audience :: Developers
Classifier: License :: OSI Approved :: MIT License
Classifier: Programming Language :: Python :: 3
Classifier: Programming Language :: Python :: 3.8
Classifier: Programming Language :: Python :: 3.9
Classifier: Programming Language :: Python :: 3.10
Classifier: Programming Language :: Python :: 3.11
Classifier: Programming Language :: Python :: 3
Classifier: Programming Language :: Python :: 3.10
Classifier: Programming Language :: Python :: 3.8
Classifier: Programming Language :: Python :: 3.9
Project-URL: Repository, https://github.com/scholarsportal/ask_schools
